django5_upyun_storage/__init__.py
django5_upyun_storage/apps.py
django5_upyun_storage/storage.py
django5_upyun_storage/tests/__init__.py
django5_upyun_storage-1.0.4.dist-info/LICENSE
django5_upyun_storage-1.0.4.dist-info/METADATA
django5_upyun_storage-1.0.4.dist-info/WHEEL
django5_upyun_storage-1.0.4.dist-info/top_level.txt
django5_upyun_storage-1.0.4.dist-info/RECORD
