Metadata-Version: 2.1
Name: django5-upyun-storage
Version: 1.0.4
Summary: 又拍云 Django5 存储后端
Home-page: https://github.com/mircool/django-upyun-storage.git
Author: Mircool
License: UNKNOWN
Project-URL: Bug Tracker, https://github.com/mircool/django-upyun-storage/issues
Keywords: django,upyun,storage,file upload
Platform: UNKNOWN
Classifier: Development Status :: 5 - Production/Stable
Classifier: Environment :: Web Environment
Classifier: Framework :: Django
Classifier: Framework :: Django :: 5.0
Classifier: Intended Audience :: Developers
Classifier: License :: OSI Approved :: MIT License
Classifier: Operating System :: OS Independent
Classifier: Programming Language :: Python :: 3
Classifier: Programming Language :: Python :: 3.8
Classifier: Programming Language :: Python :: 3.9
Classifier: Programming Language :: Python :: 3.10
Classifier: Programming Language :: Python :: 3.11
Classifier: Programming Language :: Python :: 3.12
Classifier: Topic :: Internet :: WWW/HTTP
Requires-Python: >=3.8
License-File: LICENSE
Requires-Dist: Django>=5.0
Requires-Dist: upyun>=2.5.5
